AUTHORS
COPYING
INSTALL
MANIFEST.in
setup.cfg
setup.py
SmartHTTP.egg-info/PKG-INFO
SmartHTTP.egg-info/SOURCES.txt
SmartHTTP.egg-info/dependency_links.txt
SmartHTTP.egg-info/entry_points.txt
SmartHTTP.egg-info/not-zip-safe
SmartHTTP.egg-info/requires.txt
SmartHTTP.egg-info/top_level.txt
smarthttp/__init__.py
smarthttp/asserts.py
smarthttp/decorators.py
smarthttp/exceptions.py
smarthttp/http.py
smarthttp/xml.py
smarthttp/client/__init__.py
smarthttp/client/browsers.py
smarthttp/client/platforms.py
smarthttp/client/ua.txt
smarthttp/commands/__init__.py
smarthttp/commands/httpbot.py
smarthttp/commands/pylonsscript.py
smarthttp/commands/simplebot.py
smarthttp/envspec/__init__.py
smarthttp/envspec/etree.py
smarthttp/envspec/http.py
smarthttp/envspec/js.py
smarthttp/envspec/cpython/__init__.py
smarthttp/envspec/cpython/etree.py
smarthttp/envspec/cpython/http.py
smarthttp/envspec/cpython/js.py
smarthttp/envspec/jython/__init__.py
smarthttp/envspec/jython/etree.py
smarthttp/envspec/jython/http.py
smarthttp/envspec/jython/js.py
smarthttp/envspec/pure/__init__.py
smarthttp/envspec/pure/etree.py
smarthttp/envspec/pure/http.py
smarthttp/envspec/pure/js.py
smarthttp/gui/__init__.py
smarthttp/html/__init__.py
smarthttp/html/js.py
smarthttp/html/microformats.py
smarthttp/lang/__init__.py
smarthttp/lang/ja_kana.txt
smarthttp/lang/ja_kanji.txt
smarthttp/lang/translit.py
smarthttp/lang/translit.txt
smarthttp/lang/unicode_blocks.txt
smarthttp/lib/__init__.py
smarthttp/lib/containers.py
smarthttp/proxies/__init__.py
smarthttp/sites/__init__.py
smarthttp/sites/arbitrary.py
smarthttp/sites/manager.py
smarthttp/sites/blogs/__init__.py
smarthttp/sites/blogs/blogspot.py
smarthttp/sites/blogs/livejournal.py
smarthttp/sites/blogs/wordpress.py
smarthttp/sites/bookmarks/__init__.py
smarthttp/sites/bookmarks/digg.py
smarthttp/sites/bookmarks/reddit.py
smarthttp/sites/bookmarks/slashdot.py
smarthttp/sites/cites/__init__.py
smarthttp/sites/cites/bashorgru.py
smarthttp/sites/cms/__init__.py
smarthttp/sites/cms/joomla.py
smarthttp/sites/dns/__init__.py
smarthttp/sites/dns/nomina.py
smarthttp/sites/email/__init__.py
smarthttp/sites/email/mailru.py
smarthttp/sites/forums/__init__.py
smarthttp/sites/forums/invision.py
